{
  "schemaVersion": 1,
  "title": "대외활동 큐레이션",
  "summary": "내 조건에 맞는 대외활동·공모전·장학만 골라주는 서비스입니다.",
  "githubUser": "jaeho9338-code(이재호)",
  "demoUrl": "",
  "thumbnail": "thumbnail.webp",
  "screenshots": [
    "screenshots/home.webp"
  ],
  "problem": "대외활동·공모전 정보가 여러 사이트에 흩어져 있고, 각 사이트는 모든 공고를 보여줄 뿐이라 내가 실제로 지원할 수 있는 건 자격요건을 하나하나 읽어 직접 걸러야 합니다. 그러다 놓치거나, 자격 미달인데 지원해 시간을 버립니다.",
  "targetUsers": [
    "대외활동·공모전·장학을 찾는 대학생",
    "여러 사이트를 다 뒤질 시간은 없고, 내 조건에 맞는 걸 놓치고 싶지 않은 사람"
  ],
  "features": [
    "여러 사이트에 흩어진 공고를 한곳에 모읍니다(실데이터 3,900건 이상).",
    "내 학년·전공·지역 등 조건에 맞춰 지원 가능/거의 가능/확인 필요/지원 불가로 나눠 보여줍니다.",
    "지원할 수 없는 공고는 어떤 조건이 왜 안 맞는지 사유까지 보여줍니다.",
    "상세 화면에서 막힌 조건을 바로 고치면 즉시 다시 판정합니다."
  ],
  "featureTags": [
    "공고 통합 수집",
    "자격 매칭",
    "불가 사유 표시"
  ],
  "techStack": [
    "React",
    "Vite",
    "Supabase",
    "Node.js"
  ],
  "techHighlights": [
    "Express 서버 없이 React가 Supabase를 직접 조회하고, 매칭도 화면 쪽 자바스크립트에서 계산합니다.",
    "5개 소스(콘테스트코리아·링커리어·위비티·부산청년플랫폼·온통청년)를 Node 스크립트로 수집해 하나의 postings 테이블에 통합합니다.",
    "핵심 순수 함수(매칭·지역판별·마감일)는 테스트를 먼저 쓰고 구현했고, 검증 에이전트가 실제 코드에서 버그를 잡았습니다."
  ],
  "developmentWithAI": "저는 문제와 핵심 기능, 방향을 정했습니다. AI는 요구사항을 작업으로 나누고 코드를 짰습니다. 저는 만든 것을 직접 돌리고 테스트하며 검증했고, 아니라고 판단되는 부분은 다시 방향을 잡아 고쳤습니다. 예를 들어 나이 조건은 사용자층이 대학생이라 늘 만족이라 매칭에서 걸러낼 일이 없어, 노이즈로 판단해 프로젝트 전체에서 걷어냈습니다.",
  "agent": {
    "summary": "계획-개발-검증-올리기의 하루 사이클을 스킬과 에이전트로 연결해 진행했습니다.",
    "agentTools": [
      {
        "type": "agent",
        "name": "코드 검증 에이전트(code-reviewer)",
        "purpose": "올리기 전 변경을 훑어 정확성 버그·중복·복잡도·테스트 유무·비밀값을 짚습니다."
      },
      {
        "type": "skill",
        "name": "계획 수립 스킬(task-planner)",
        "purpose": "목표를 하루 크기 작업으로 나누고 우선순위·완료 기준을 매깁니다."
      },
      {
        "type": "skill",
        "name": "테스트 작성 스킬(test-writer)",
        "purpose": "새 로직을 테스트 먼저 쓰고 통과시키는 TDD 흐름을 안내합니다."
      },
      {
        "type": "skill",
        "name": "기능 검증 스킬(feature-verifier)",
        "purpose": "됐다고 넘기지 않고 실제로 돌려서 요구대로 동작하는지 확인합니다."
      }
    ],
    "workflows": [
      {
        "name": "기능 개발 Workflow",
        "steps": [
          "이번 주 목표를 하루 크기 작업으로 분해",
          "GitHub Issue로 등록",
          "작게 쪼갠 커밋으로 개발(순수 함수는 테스트 먼저)",
          "기능 검증 스킬로 실제 동작 확인"
        ]
      },
      {
        "name": "검증·올리기 Workflow",
        "steps": [
          "코드 검증 에이전트로 변경 점검",
          "지적받은 문제 수정(다시 테스트)",
          "비밀값 검사 후 브랜치 push",
          "hub 미러 PR 작성"
        ]
      }
    ]
  }
}
